odb/__init__.py
odb/cli.py
odb/odb.py
odb/test.py
anybox.pg.odoo-0.7.dist-info/METADATA
anybox.pg.odoo-0.7.dist-info/WHEEL
anybox.pg.odoo-0.7.dist-info/entry_points.txt
anybox.pg.odoo-0.7.dist-info/top_level.txt
anybox.pg.odoo-0.7.dist-info/RECORD
