Metadata-Version: 2.1
Name: anybox.pg.odoo
Version: 0.7
Summary: Postgresql database snapshot versionning tool
Home-page: 
Author: Christophe Combelles
Author-email: ccomb@anybox.fr
License: GPLv3
Keywords: odb postgresql odoo snapshot commit version
Classifier: Development Status :: 4 - Beta
Classifier: Environment :: Console
Classifier: Intended Audience :: Developers
Classifier: Intended Audience :: System Administrators
Classifier: License :: OSI Approved :: GNU General Public License v3 or later (GPLv3+)
Classifier: Programming Language :: Python :: 2
Classifier: Programming Language :: Python :: 3
Classifier: Topic :: Database
Classifier: Topic :: Software Development :: Version Control
Classifier: Topic :: Utilities
Requires-Dist: psycopg2-binary
